normandy/__init__.py
normandy/normandy.py
normandy/engine/__init__.py
normandy/engine/errors.py
normandy/engine/logger.py
normandy/engine/pipeline.py
normandy/engine/tools.py
normandy/engine/variables_storage.py
normandy-0.3.dist-info/LICENSE
normandy-0.3.dist-info/METADATA
normandy-0.3.dist-info/WHEEL
normandy-0.3.dist-info/entry_points.txt
normandy-0.3.dist-info/top_level.txt
normandy-0.3.dist-info/RECORD
