Metadata-Version: 2.1
Name: normandy
Version: 0.3
Summary: A data pipeline framework.
Home-page: https://github.com/echang1802/normandy
Author: Eloy Chang
Author-email: echang.epsilondl@gmail.com
License: UNKNOWN
Platform: UNKNOWN
Classifier: Programming Language :: Python :: 3
Classifier: License :: OSI Approved :: MIT License
Classifier: Operating System :: OS Independent
Requires-Python: >=3.6
License-File: LICENSE
